fabz_placeholder.py
fabz-0.0.1.dist-info/METADATA
fabz-0.0.1.dist-info/WHEEL
fabz-0.0.1.dist-info/entry_points.txt
fabz-0.0.1.dist-info/top_level.txt
fabz-0.0.1.dist-info/RECORD
